TSUtilities/__init__.py
TSUtilities/functions.py
TSUtilities/generate_series.py
TSUtilities/get_features.py
TSUtilities/split_ts.py
TSUtilities/TSFeatures/__init__.py
TSUtilities/TSFeatures/fourier_seasonality.py
TSUtilities/TSFeatures/linear_changepoint.py
TSUtilities/TSTrend/__init__.py
TSUtilities/TSTrend/trend_dampen.py
TSUtilities-0.0.5.dist-info/LICENSE
TSUtilities-0.0.5.dist-info/METADATA
TSUtilities-0.0.5.dist-info/WHEEL
TSUtilities-0.0.5.dist-info/top_level.txt
TSUtilities-0.0.5.dist-info/RECORD
